argument_esa_model/__init__.py
argument_esa_model/compute-esa-matrix.py
argument_esa_model/esa.py
argument_esa_model/esa_all_terms.py
argument_esa_model/esa_top_n_terms.py
argument_esa_model/main.py
argument_esa_model/matrix.py
argument_esa_model/preprocessor.py
argument_esa_model/similarity.py
argument_esa_model-3.11.112.dist-info/LICENSE
argument_esa_model-3.11.112.dist-info/METADATA
argument_esa_model-3.11.112.dist-info/WHEEL
argument_esa_model-3.11.112.dist-info/top_level.txt
argument_esa_model-3.11.112.dist-info/RECORD
